{
	"dataVersionList": [
		{
			"tableName": "asset_category_m",
			"version": "1223",
			"cacheVersion": "1223"
		},
		{
			"tableName": "monster_m",
			"version": "1318",
			"cacheVersion": "1318"
		},
		{
			"tableName": "monster_evolution_m",
			"version": "1273",
			"cacheVersion": "1273"
		},
		{
			"tableName": "monster_experience_m",
			"version": "1216",
			"cacheVersion": "1216"
		},
		{
			"tableName": "skill_m",
			"version": "1317",
			"cacheVersion": "1317"
		},
		{
			"tableName": "skill_detail_m",
			"version": "1331",
			"cacheVersion": "1331"
		},
		{
			"tableName": "monster_evolution_route_m",
			"version": "1232",
			"cacheVersion": "1232"
		},
		{
			"tableName": "soul_m",
			"version": "1252",
			"cacheVersion": "1252"
		},
		{
			"tableName": "monster_resistance_m",
			"version": "1307",
			"cacheVersion": "1307"
		},
		{
			"tableName": "facility_m",
			"version": "1246",
			"cacheVersion": "1246"
		},
		{
			"tableName": "facility_upgrade_m",
			"version": "1219",
			"cacheVersion": "1219"
		},
		{
			"tableName": "facility_meat_field_m",
			"version": "1216",
			"cacheVersion": "1216"
		},
		{
			"tableName": "facility_warehouse_m",
			"version": "1216",
			"cacheVersion": "1216"
		},
		{
			"tableName": "facility_exp_up_m",
			"version": "1216",
			"cacheVersion": "1216"
		},
		{
			"tableName": "facility_restaurant_m",
			"version": "1216",
			"cacheVersion": "1216"
		},
		{
			"tableName": "facility_house_m",
			"version": "1216",
			"cacheVersion": "1216"
		},
		{
			"tableName": "facility_condition_m",
			"version": "1219",
			"cacheVersion": "1219"
		},
		{
			"tableName": "world_area_m",
			"version": "1300",
			"cacheVersion": "1300"
		},
		{
			"tableName": "world_stage_m",
			"version": "1330",
			"cacheVersion": "1330"
		},
		{
			"tableName": "world_dungeon_m",
			"version": "1371",
			"cacheVersion": "1371"
		},
		{
			"tableName": "monster_tribe_m",
			"version": "1216",
			"cacheVersion": "1216"
		},
		{
			"tableName": "monster_grow_step_m",
			"version": "1217",
			"cacheVersion": "1217"
		},
		{
			"tableName": "tips_m",
			"version": "1235",
			"cacheVersion": "1235"
		},
		{
			"tableName": "help_category_m",
			"version": "1225",
			"cacheVersion": "1225"
		},
		{
			"tableName": "help_m",
			"version": "1247",
			"cacheVersion": "1247"
		},
		{
			"tableName": "tutorial_navi_m",
			"version": "1233",
			"cacheVersion": "1233"
		},
		{
			"tableName": "monster_trance_m",
			"version": "1262",
			"cacheVersion": "1262"
		},
		{
			"tableName": "monster_tribe_trance_m",
			"version": "1216",
			"cacheVersion": "1216"
		},
		{
			"tableName": "code_m",
			"version": "1238",
			"cacheVersion": "1238"
		},
		{
			"tableName": "message_m",
			"version": "1247",
			"cacheVersion": "1247"
		},
		{
			"tableName": "item_m",
			"version": "1288",
			"cacheVersion": "1288"
		},
		{
			"tableName": "world_dungeon_reward_m",
			"version": "1334",
			"cacheVersion": "1334"
		},
		{
			"tableName": "colosseum_m",
			"version": "1249",
			"cacheVersion": "1249"
		},
		{
			"tableName": "colosseum_time_schedule_m",
			"version": "1259",
			"cacheVersion": "1259"
		},
		{
			"tableName": "world_dungeon_extra_effect_m",
			"version": "1259",
			"cacheVersion": "1259"
		},
		{
			"tableName": "world_dungeon_extra_effect_manage_m",
			"version": "1255",
			"cacheVersion": "1255"
		},
		{
			"tableName": "monster_evolution_material_m",
			"version": "1266",
			"cacheVersion": "1266"
		},
		{
			"tableName": "chip_m",
			"version": "1310",
			"cacheVersion": "1310"
		},
		{
			"tableName": "chip_effect_m",
			"version": "1307",
			"cacheVersion": "1307"
		},
		{
			"tableName": "message_string_m",
			"version": "1235",
			"cacheVersion": "1235"
		},
		{
			"tableName": "world_event_m",
			"version": "1290",
			"cacheVersion": "1290"
		},
		{
			"tableName": "world_event_area_m",
			"version": "1285",
			"cacheVersion": "1285"
		},
		{
			"tableName": "event_point_achieve_reward_m",
			"version": "1248",
			"cacheVersion": "1248"
		},
		{
			"tableName": "event_point_bonus_m",
			"version": "1253",
			"cacheVersion": "1253"
		},
		{
			"tableName": "event_ranking_reward_m",
			"version": "1237",
			"cacheVersion": "1237"
		},
		{
			"tableName": "facility_key_m",
			"version": "1216",
			"cacheVersion": "1216"
		},
		{
			"tableName": "facility_chip_m",
			"version": "1216",
			"cacheVersion": "1216"
		},
		{
			"tableName": "monster_fixed_value_m",
			"version": "1255",
			"cacheVersion": "1255"
		},
		{
			"tableName": "navigation_message_m",
			"version": "1218",
			"cacheVersion": "1218"
		},
		{
			"tableName": "dungeon_ticket_m",
			"version": "1220",
			"cacheVersion": "1220"
		},
		{
			"tableName": "colosseum_event_m",
			"version": "1216",
			"cacheVersion": "1216"
		},
		{
			"tableName": "colosseum_rank_m",
			"version": "1220",
			"cacheVersion": "1220"
		},
		{
			"tableName": "title_m",
			"version": "1228",
			"cacheVersion": "1228"
		},
		{
			"tableName": "ability_upgrade_rate_m",
			"version": "1217",
			"cacheVersion": "1217"
		},
		{
			"tableName": "world_dungeon_sortie_limit_m",
			"version": "1217",
			"cacheVersion": "1217"
		},
		{
			"tableName": "monster_status_ailment_material_m",
			"version": "1217",
			"cacheVersion": "1217"
		},
		{
			"tableName": "monster_status_ailment_m",
			"version": "1224",
			"cacheVersion": "1224"
		},
		{
			"tableName": "monster_integration_group_m",
			"version": "1219",
			"cacheVersion": "1219"
		},
		{
			"tableName": "monster_status_m",
			"version": "1218",
			"cacheVersion": "1218"
		},
		{
			"tableName": "monster_sell_recover_item_m",
			"version": "1243",
			"cacheVersion": "1243"
		},
		{
			"tableName": "monster_rare_m",
			"version": "1217",
			"cacheVersion": "1217"
		},
		{
			"tableName": "world_dungeon_adventure_scene_m",
			"version": "1220",
			"cacheVersion": "1220"
		},
		{
			"tableName": "world_dungeon_option_reward_m",
			"version": "1218",
			"cacheVersion": "1218"
		},
		{
			"tableName": "banner_m",
			"version": "1235",
			"cacheVersion": "1235"
		},
		{
			"tableName": "world_stage_force_open_m",
			"version": "872",
			"cacheVersion": "872"
		},
		{
			"tableName": "asset_sales_bonus_m",
			"version": "879",
			"cacheVersion": "879"
		},
		{
			"tableName": "monster_auto_load_chip_m",
			"version": "872",
			"cacheVersion": "872"
		}
	],
	"versionManagerMaster": {
		"versionManagerId": "5",
		"versionManagerType": "2",
		"osType": "2",
		"version": "402"
	}
}