{
	"dataVersionList": [
		{
			"tableName": "asset_category_m",
			"version": "694",
			"cacheVersion": "694"
		},
		{
			"tableName": "monster_m",
			"version": "784",
			"cacheVersion": "784"
		},
		{
			"tableName": "monster_evolution_m",
			"version": "737",
			"cacheVersion": "737"
		},
		{
			"tableName": "monster_experience_m",
			"version": "687",
			"cacheVersion": "687"
		},
		{
			"tableName": "skill_m",
			"version": "785",
			"cacheVersion": "785"
		},
		{
			"tableName": "skill_detail_m",
			"version": "798",
			"cacheVersion": "798"
		},
		{
			"tableName": "monster_evolution_route_m",
			"version": "703",
			"cacheVersion": "703"
		},
		{
			"tableName": "soul_m",
			"version": "723",
			"cacheVersion": "723"
		},
		{
			"tableName": "monster_resistance_m",
			"version": "777",
			"cacheVersion": "777"
		},
		{
			"tableName": "facility_m",
			"version": "717",
			"cacheVersion": "717"
		},
		{
			"tableName": "facility_upgrade_m",
			"version": "690",
			"cacheVersion": "690"
		},
		{
			"tableName": "facility_meat_field_m",
			"version": "687",
			"cacheVersion": "687"
		},
		{
			"tableName": "facility_warehouse_m",
			"version": "687",
			"cacheVersion": "687"
		},
		{
			"tableName": "facility_exp_up_m",
			"version": "687",
			"cacheVersion": "687"
		},
		{
			"tableName": "facility_restaurant_m",
			"version": "687",
			"cacheVersion": "687"
		},
		{
			"tableName": "facility_house_m",
			"version": "687",
			"cacheVersion": "687"
		},
		{
			"tableName": "facility_condition_m",
			"version": "690",
			"cacheVersion": "690"
		},
		{
			"tableName": "world_area_m",
			"version": "771",
			"cacheVersion": "771"
		},
		{
			"tableName": "world_stage_m",
			"version": "801",
			"cacheVersion": "801"
		},
		{
			"tableName": "world_dungeon_m",
			"version": "840",
			"cacheVersion": "840"
		},
		{
			"tableName": "monster_tribe_m",
			"version": "687",
			"cacheVersion": "687"
		},
		{
			"tableName": "monster_grow_step_m",
			"version": "688",
			"cacheVersion": "688"
		},
		{
			"tableName": "tips_m",
			"version": "706",
			"cacheVersion": "706"
		},
		{
			"tableName": "help_category_m",
			"version": "696",
			"cacheVersion": "696"
		},
		{
			"tableName": "help_m",
			"version": "718",
			"cacheVersion": "718"
		},
		{
			"tableName": "tutorial_navi_m",
			"version": "703",
			"cacheVersion": "703"
		},
		{
			"tableName": "monster_trance_m",
			"version": "732",
			"cacheVersion": "732"
		},
		{
			"tableName": "monster_tribe_trance_m",
			"version": "687",
			"cacheVersion": "687"
		},
		{
			"tableName": "code_m",
			"version": "709",
			"cacheVersion": "709"
		},
		{
			"tableName": "message_m",
			"version": "718",
			"cacheVersion": "718"
		},
		{
			"tableName": "item_m",
			"version": "753",
			"cacheVersion": "753"
		},
		{
			"tableName": "world_dungeon_reward_m",
			"version": "805",
			"cacheVersion": "805"
		},
		{
			"tableName": "colosseum_m",
			"version": "720",
			"cacheVersion": "720"
		},
		{
			"tableName": "colosseum_time_schedule_m",
			"version": "730",
			"cacheVersion": "730"
		},
		{
			"tableName": "world_dungeon_extra_effect_m",
			"version": "730",
			"cacheVersion": "730"
		},
		{
			"tableName": "world_dungeon_extra_effect_manage_m",
			"version": "726",
			"cacheVersion": "726"
		},
		{
			"tableName": "monster_evolution_material_m",
			"version": "731",
			"cacheVersion": "731"
		},
		{
			"tableName": "chip_m",
			"version": "772",
			"cacheVersion": "772"
		},
		{
			"tableName": "chip_effect_m",
			"version": "776",
			"cacheVersion": "776"
		},
		{
			"tableName": "message_string_m",
			"version": "706",
			"cacheVersion": "706"
		},
		{
			"tableName": "world_event_m",
			"version": "761",
			"cacheVersion": "761"
		},
		{
			"tableName": "world_event_area_m",
			"version": "756",
			"cacheVersion": "756"
		},
		{
			"tableName": "event_point_achieve_reward_m",
			"version": "718",
			"cacheVersion": "718"
		},
		{
			"tableName": "event_point_bonus_m",
			"version": "721",
			"cacheVersion": "721"
		},
		{
			"tableName": "event_ranking_reward_m",
			"version": "708",
			"cacheVersion": "708"
		},
		{
			"tableName": "facility_key_m",
			"version": "687",
			"cacheVersion": "687"
		},
		{
			"tableName": "facility_chip_m",
			"version": "687",
			"cacheVersion": "687"
		},
		{
			"tableName": "monster_fixed_value_m",
			"version": "724",
			"cacheVersion": "724"
		},
		{
			"tableName": "navigation_message_m",
			"version": "689",
			"cacheVersion": "689"
		},
		{
			"tableName": "dungeon_ticket_m",
			"version": "691",
			"cacheVersion": "691"
		},
		{
			"tableName": "colosseum_event_m",
			"version": "687",
			"cacheVersion": "687"
		},
		{
			"tableName": "colosseum_rank_m",
			"version": "691",
			"cacheVersion": "691"
		},
		{
			"tableName": "title_m",
			"version": "699",
			"cacheVersion": "699"
		},
		{
			"tableName": "ability_upgrade_rate_m",
			"version": "688",
			"cacheVersion": "688"
		},
		{
			"tableName": "world_dungeon_sortie_limit_m",
			"version": "688",
			"cacheVersion": "688"
		},
		{
			"tableName": "monster_status_ailment_material_m",
			"version": "688",
			"cacheVersion": "688"
		},
		{
			"tableName": "monster_status_ailment_m",
			"version": "693",
			"cacheVersion": "693"
		},
		{
			"tableName": "monster_integration_group_m",
			"version": "690",
			"cacheVersion": "690"
		},
		{
			"tableName": "monster_status_m",
			"version": "689",
			"cacheVersion": "689"
		},
		{
			"tableName": "monster_sell_recover_item_m",
			"version": "714",
			"cacheVersion": "714"
		},
		{
			"tableName": "monster_rare_m",
			"version": "688",
			"cacheVersion": "688"
		},
		{
			"tableName": "world_dungeon_adventure_scene_m",
			"version": "691",
			"cacheVersion": "691"
		},
		{
			"tableName": "world_dungeon_option_reward_m",
			"version": "689",
			"cacheVersion": "689"
		},
		{
			"tableName": "banner_m",
			"version": "698",
			"cacheVersion": "698"
		},
		{
			"tableName": "world_stage_force_open_m",
			"version": "343",
			"cacheVersion": "343"
		},
		{
			"tableName": "asset_sales_bonus_m",
			"version": "345",
			"cacheVersion": "345"
		},
		{
			"tableName": "monster_auto_load_chip_m",
			"version": "343",
			"cacheVersion": "343"
		}
	],
	"versionManagerMaster": {
		"versionManagerId": "5",
		"versionManagerType": "2",
		"osType": "2",
		"version": "344"
	}
}