{
	"dataVersionList": [
		{
			"tableName": "asset_category_m",
			"version": "422",
			"cacheVersion": "422"
		},
		{
			"tableName": "monster_m",
			"version": "502",
			"cacheVersion": "502"
		},
		{
			"tableName": "monster_evolution_m",
			"version": "444",
			"cacheVersion": "444"
		},
		{
			"tableName": "monster_experience_m",
			"version": "414",
			"cacheVersion": "414"
		},
		{
			"tableName": "skill_m",
			"version": "509",
			"cacheVersion": "509"
		},
		{
			"tableName": "skill_detail_m",
			"version": "515",
			"cacheVersion": "515"
		},
		{
			"tableName": "monster_evolution_route_m",
			"version": "426",
			"cacheVersion": "426"
		},
		{
			"tableName": "soul_m",
			"version": "435",
			"cacheVersion": "435"
		},
		{
			"tableName": "monster_resistance_m",
			"version": "473",
			"cacheVersion": "473"
		},
		{
			"tableName": "facility_m",
			"version": "444",
			"cacheVersion": "444"
		},
		{
			"tableName": "facility_upgrade_m",
			"version": "417",
			"cacheVersion": "417"
		},
		{
			"tableName": "facility_meat_field_m",
			"version": "414",
			"cacheVersion": "414"
		},
		{
			"tableName": "facility_warehouse_m",
			"version": "414",
			"cacheVersion": "414"
		},
		{
			"tableName": "facility_exp_up_m",
			"version": "414",
			"cacheVersion": "414"
		},
		{
			"tableName": "facility_restaurant_m",
			"version": "414",
			"cacheVersion": "414"
		},
		{
			"tableName": "facility_house_m",
			"version": "414",
			"cacheVersion": "414"
		},
		{
			"tableName": "facility_condition_m",
			"version": "418",
			"cacheVersion": "418"
		},
		{
			"tableName": "world_area_m",
			"version": "509",
			"cacheVersion": "509"
		},
		{
			"tableName": "world_stage_m",
			"version": "530",
			"cacheVersion": "530"
		},
		{
			"tableName": "world_dungeon_m",
			"version": "590",
			"cacheVersion": "590"
		},
		{
			"tableName": "monster_tribe_m",
			"version": "416",
			"cacheVersion": "416"
		},
		{
			"tableName": "monster_grow_step_m",
			"version": "415",
			"cacheVersion": "415"
		},
		{
			"tableName": "tips_m",
			"version": "433",
			"cacheVersion": "433"
		},
		{
			"tableName": "help_category_m",
			"version": "424",
			"cacheVersion": "424"
		},
		{
			"tableName": "help_m",
			"version": "450",
			"cacheVersion": "450"
		},
		{
			"tableName": "tutorial_navi_m",
			"version": "445",
			"cacheVersion": "445"
		},
		{
			"tableName": "monster_trance_m",
			"version": "438",
			"cacheVersion": "438"
		},
		{
			"tableName": "monster_tribe_trance_m",
			"version": "414",
			"cacheVersion": "414"
		},
		{
			"tableName": "code_m",
			"version": "435",
			"cacheVersion": "435"
		},
		{
			"tableName": "message_m",
			"version": "446",
			"cacheVersion": "446"
		},
		{
			"tableName": "item_m",
			"version": "484",
			"cacheVersion": "484"
		},
		{
			"tableName": "world_dungeon_reward_m",
			"version": "530",
			"cacheVersion": "530"
		},
		{
			"tableName": "colosseum_m",
			"version": "456",
			"cacheVersion": "456"
		},
		{
			"tableName": "colosseum_time_schedule_m",
			"version": "462",
			"cacheVersion": "462"
		},
		{
			"tableName": "world_dungeon_extra_effect_m",
			"version": "462",
			"cacheVersion": "462"
		},
		{
			"tableName": "world_dungeon_extra_effect_manage_m",
			"version": "450",
			"cacheVersion": "450"
		},
		{
			"tableName": "monster_evolution_material_m",
			"version": "438",
			"cacheVersion": "438"
		},
		{
			"tableName": "chip_m",
			"version": "531",
			"cacheVersion": "531"
		},
		{
			"tableName": "chip_effect_m",
			"version": "501",
			"cacheVersion": "501"
		},
		{
			"tableName": "message_string_m",
			"version": "468",
			"cacheVersion": "468"
		},
		{
			"tableName": "world_event_m",
			"version": "537",
			"cacheVersion": "537"
		},
		{
			"tableName": "world_event_area_m",
			"version": "488",
			"cacheVersion": "488"
		},
		{
			"tableName": "event_point_achieve_reward_m",
			"version": "440",
			"cacheVersion": "440"
		},
		{
			"tableName": "event_point_bonus_m",
			"version": "474",
			"cacheVersion": "474"
		},
		{
			"tableName": "event_ranking_reward_m",
			"version": "434",
			"cacheVersion": "434"
		},
		{
			"tableName": "facility_key_m",
			"version": "415",
			"cacheVersion": "415"
		},
		{
			"tableName": "facility_chip_m",
			"version": "414",
			"cacheVersion": "414"
		},
		{
			"tableName": "monster_fixed_value_m",
			"version": "441",
			"cacheVersion": "441"
		},
		{
			"tableName": "navigation_message_m",
			"version": "414",
			"cacheVersion": "414"
		},
		{
			"tableName": "dungeon_ticket_m",
			"version": "421",
			"cacheVersion": "421"
		},
		{
			"tableName": "colosseum_event_m",
			"version": "414",
			"cacheVersion": "414"
		},
		{
			"tableName": "colosseum_rank_m",
			"version": "415",
			"cacheVersion": "415"
		},
		{
			"tableName": "title_m",
			"version": "419",
			"cacheVersion": "419"
		},
		{
			"tableName": "ability_upgrade_rate_m",
			"version": "415",
			"cacheVersion": "415"
		},
		{
			"tableName": "world_dungeon_sortie_limit_m",
			"version": "415",
			"cacheVersion": "415"
		},
		{
			"tableName": "monster_status_ailment_material_m",
			"version": "415",
			"cacheVersion": "415"
		},
		{
			"tableName": "monster_status_ailment_m",
			"version": "416",
			"cacheVersion": "416"
		},
		{
			"tableName": "monster_integration_group_m",
			"version": "416",
			"cacheVersion": "416"
		},
		{
			"tableName": "monster_status_m",
			"version": "416",
			"cacheVersion": "416"
		},
		{
			"tableName": "monster_sell_recover_item_m",
			"version": "419",
			"cacheVersion": "419"
		},
		{
			"tableName": "monster_rare_m",
			"version": "417",
			"cacheVersion": "417"
		},
		{
			"tableName": "world_dungeon_adventure_scene_m",
			"version": "442",
			"cacheVersion": "442"
		},
		{
			"tableName": "world_dungeon_option_reward_m",
			"version": "417",
			"cacheVersion": "417"
		},
		{
			"tableName": "banner_m",
			"version": "458",
			"cacheVersion": "458"
		},
		{
			"tableName": "world_stage_force_open_m",
			"version": "344",
			"cacheVersion": "344"
		},
		{
			"tableName": "asset_sales_bonus_m",
			"version": "343",
			"cacheVersion": "343"
		},
		{
			"tableName": "monster_auto_load_chip_m",
			"version": "343",
			"cacheVersion": "343"
		}
	],
	"versionManagerMaster": {
		"versionManagerId": "5",
		"versionManagerType": "2",
		"osType": "2",
		"version": "371"
	}
}